sybil_bin/__init__.py
sybil_bin/main.py
sybil_bin/setup.py
sybil_bin/binaries/linux/sybil.amd64
sybil_bin/binaries/mac/sybil.arm64
sybil_bin-0.5.2.data/data/sybil_bin/binaries/linux/sybil.amd64
sybil_bin-0.5.2.dist-info/METADATA
sybil_bin-0.5.2.dist-info/WHEEL
sybil_bin-0.5.2.dist-info/top_level.txt
sybil_bin-0.5.2.dist-info/RECORD
