Metadata-Version: 2.1
Name: sybil-bin
Version: 0.5.2
Summary: A sybil binary package with platform-specific binaries
Home-page: UNKNOWN
Author: UNKNOWN
Author-email: UNKNOWN
License: UNKNOWN
Platform: UNKNOWN
